gstargets/__init__.py
gstargets/config.py
gstargets/main.py
gstargets/reversal.py
gstargets/shared.py
gstargets/target_point.py
gstargets-0.2.9.dist-info/WHEEL
gstargets-0.2.9.dist-info/METADATA
gstargets-0.2.9.dist-info/RECORD
